{
  "latest_minute": {
    "collected_at_utc": "2026-04-18T14:15:36.288761Z",
    "product_id": "BTC-USD",
    "depth": 10,
    "imbalance": 0.787071778255,
    "mid_price": 76192.705,
    "spread_bps": 0.001312461608,
    "status": "ok"
  },
  "latest_hourly": {
    "window_start_utc": "2026-04-18T13:16:36.288632Z",
    "window_end_utc": "2026-04-18T14:15:36.626600Z",
    "product_id": "BTC-USD",
    "depth": 10,
    "successful_samples": 60,
    "failed_samples": 0,
    "imbalance_mean": -0.170314895426,
    "imbalance_median": -0.253627767396,
    "imbalance_min": -0.929955451635,
    "imbalance_max": 0.819369616541
  }
}
